drawsbml/__main__.py
drawsbml-0.1.3.dist-info/entry_points.txt
drawsbml-0.1.3.dist-info/LICENSE
drawsbml-0.1.3.dist-info/WHEEL
drawsbml-0.1.3.dist-info/METADATA
drawsbml-0.1.3.dist-info/RECORD
