Metadata-Version: 2.1
Name: drawsbml
Version: 0.1.3
Summary: Draw Signalling Pathways (SBML) using graphviz
License: GPLv3
Author: Dilawar Singh
Author-email: dilawar.s.rajput@gmail.com
Requires-Python: >=3.7,<4.0
Classifier: License :: Other/Proprietary License
Classifier: Programming Language :: Python :: 3
Classifier: Programming Language :: Python :: 3.7
Classifier: Programming Language :: Python :: 3.8
Classifier: Programming Language :: Python :: 3.9
Requires-Dist: networkx (>=2.5.1,<3.0.0)
Requires-Dist: pydot (>=1.4.2,<2.0.0)
Requires-Dist: python-libsbml (>=5.19.0,<6.0.0)
